infrared_packstack-3.0.0.dist-info/DESCRIPTION.rst
infrared_packstack-3.0.0.dist-info/METADATA
infrared_packstack-3.0.0.dist-info/RECORD
infrared_packstack-3.0.0.dist-info/WHEEL
infrared_packstack-3.0.0.dist-info/entry_points.txt
infrared_packstack-3.0.0.dist-info/metadata.json
infrared_packstack-3.0.0.dist-info/pbr.json
infrared_packstack-3.0.0.dist-info/top_level.txt
packstack/__init__.py
packstack/configure_services_post_install.yml
packstack/create_external_network.yml
packstack/init.yml
packstack/install.yml
packstack/main.yml
packstack/plugin.spec
packstack/setup_packages.yml
packstack/vars/network/common/3_nics_common.yml
packstack/vars/network/service/neutron.yml
packstack/vars/network/service/nova.yml
packstack/vars/network/variant/neutron_gre.yml
packstack/vars/network/variant/neutron_ml2-gre.yml
packstack/vars/network/variant/neutron_ml2-vlan.yml
packstack/vars/network/variant/neutron_ml2-vxlan.yml
packstack/vars/network/variant/neutron_sriov.yml
packstack/vars/network/variant/nova_flatdhcp.yml
packstack/vars/public/subnet/default.yml
